waist/__init__.py
waist-0.1.0.dist-info/METADATA
waist-0.1.0.dist-info/WHEEL
waist-0.1.0.dist-info/top_level.txt
waist-0.1.0.dist-info/RECORD
