Metadata-Version: 2.1
Name: waist
Version: 0.1.0
Summary: API dispatch in Python
Author-email: Jerakin <the_rensvind@hotmail.com>
License: MIT
Project-URL: repository, https://github.com/jerakin/waist
Requires-Python: >=3.8
Provides-Extra: dev
Requires-Dist: pytest >=6 ; extra == 'dev'
Requires-Dist: ruff ==0.1.0 ; extra == 'dev'
Requires-Dist: build ; extra == 'dev'
Requires-Dist: twine ; extra == 'dev'
